twema/__init__.py
twema/cli.py
twema/config.py
twema/db.py
twema/formatting.py
twema/mail.py
twema/parse.py
twema/twitter.py
twema/templates/thread.jinja
twema-0.5.2.dist-info/METADATA
twema-0.5.2.dist-info/WHEEL
twema-0.5.2.dist-info/entry_points.txt
twema-0.5.2.dist-info/top_level.txt
twema-0.5.2.dist-info/RECORD
