Metadata-Version: 2.1
Name: twema
Version: 0.5.2
Summary: Twitter-to-email gateway
Home-page: https://github.com/dottedmag/twema
Author: Mikhail Gusarov
Author-email: dottedmag@dottedmag.net
License: AGPLv3
Requires-Dist: Jinja2 (==3.1.2)
Requires-Dist: toml (==0.10.0)
Requires-Dist: twitter (==1.18.0)
Requires-Dist: xdg (==4.0.1)
